setup.cfg
setup.py
pysummarize.egg-info/PKG-INFO
pysummarize.egg-info/SOURCES.txt
pysummarize.egg-info/dependency_links.txt
pysummarize.egg-info/requires.txt
pysummarize.egg-info/top_level.txt
summarize/__init__.py
summarize/language.py
summarize/summarize.py