Metadata-Version: 1.1
Name: pysummarize
Version: 0.6.0
Summary: Simple multi-language Python and NLTK-based implementation of text summarization
Home-page: https://github.com/despawnerer/summarize
Author: Aleksei Voronov
Author-email: despawn@gmail.com
License: MIT
Keywords: language nltk linguistics nlp
Platform: UNKNOWN
Classifier: Development Status :: 4 - Beta
Classifier: Intended Audience :: Developers
Classifier: Operating System :: OS Independent
Classifier: Topic :: Text Processing
Classifier: Natural Language :: English
Classifier: Natural Language :: Spanish
Classifier: License :: OSI Approved :: MIT License
Classifier: Programming Language :: Python :: 2
Classifier: Programming Language :: Python :: 2.7
Classifier: Programming Language :: Python :: 3
Classifier: Programming Language :: Python :: 3.4
Classifier: Programming Language :: Python :: 3.5
